{"identifier": "", "motion_text": "(H) PASSED Y22 N17 E1 #997", "motion_classification": ["passage"], "start_date": "2025-05-02", "result": "pass", "organization": "~{\"classification\": \"lower\"}", "legislative_session": "34", "bill": "c4d37fc6-cf9b-11f0-96bc-c2634d5a5724", "bill_action": null, "bill_identifier": "HB26", "votes": [], "counts": [{"option": "yes", "value": 22}, {"option": "no", "value": 17}, {"option": "other", "value": 1}], "sources": [{"url": "https://www.akleg.gov/basis/Journal/Pages/34?Chamber=H&Bill=HB26&Page=00997#0997", "note": ""}], "extras": {}, "_id": "c4d3fc1c-cf9b-11f0-96bc-c2634d5a5724"}